{
  "trades": [
    {
      "id": "5efb146e-e82f-4c5e-ab41-449ff2b3e93c",
      "symbol": "SHIBUSD",
      "qty": 1067120.95,
      "side": "buy",
      "reason": "signal_buy score=5.0 conf=0.5",
      "time": "2026-03-12T20:39:21.124318",
      "price": 5.87e-06
    },
    {
      "id": "ab0b469e-140d-41e4-b6cd-24035278a2f7",
      "symbol": "SHIBUSD",
      "qty": 1064453.147625,
      "side": "sell",
      "reason": "signal_sell score=1.0",
      "time": "2026-03-12T23:01:55.336558"
    },
    {
      "id": "d61987b1-208d-46ec-9f71-f8bf278918d4",
      "symbol": "LTCUSD",
      "qty": 0.1143135,
      "side": "sell",
      "reason": "signal_sell score=6.0",
      "time": "2026-03-13T00:15:59.175162"
    },
    {
      "id": "c162bc03-a8d0-4600-abee-127456d29e97",
      "symbol": "DOTUSD",
      "qty": 4.119675,
      "side": "sell",
      "reason": "signal_sell score=2.0",
      "time": "2026-03-13T10:01:26.594817"
    },
    {
      "id": "7af9bdee-1cf2-4732-a297-bca6ac46b32d",
      "symbol": "DOTUSD",
      "qty": 4.05,
      "side": "buy",
      "reason": "signal_buy score=4.0 conf=0.44",
      "time": "2026-03-13T13:03:09.377437",
      "price": 1.534195
    }
  ],
  "signals": {
    "BTC/USD": {
      "price": 71220.748,
      "rsi": 24.03,
      "sma3": 71256.336167,
      "sma9": 71716.990222,
      "sma21": 71764.496048,
      "sma50": 70808.78051,
      "macd_hist": -182.706237,
      "bb_pct": 0.285,
      "vol_ratio": 0.071,
      "vol_strong": false,
      "rsi_divergence": "none",
      "trend_slope": -0.1556,
      "trend_1h": 0.0,
      "trend_4h": 0.0022,
      "trend_24h": 0.0619,
      "stabilising": false,
      "near_support": true,
      "atr_pct": 0.0135,
      "dynamic_stop": 0.03,
      "dynamic_tp": 0.027,
      "buy_score": 3.47,
      "sell_score": 4.5,
      "final_score": 3.47,
      "signal": "BUY",
      "confidence": 0.362,
      "regime": "recovery",
      "signals_fired": [
        "trend_bear",
        "rsi_oversold",
        "near_support",
        "momentum_down"
      ],
      "timestamp": "2026-03-13T21:49:51.445187",
      "symbol": "BTC/USD"
    },
    "ETH/USD": {
      "price": 2106.85,
      "rsi": 21.58,
      "sma3": 2106.8095,
      "sma9": 2124.992889,
      "sma21": 2119.292024,
      "sma50": 2083.33463,
      "macd_hist": -5.493662,
      "bb_pct": 0.364,
      "vol_ratio": 0.069,
      "vol_strong": false,
      "rsi_divergence": "none",
      "trend_slope": -0.2121,
      "trend_1h": 0.0,
      "trend_4h": 0.0026,
      "trend_24h": 0.0811,
      "stabilising": false,
      "near_support": false,
      "atr_pct": 0.0135,
      "dynamic_stop": 0.03,
      "dynamic_tp": 0.0271,
      "buy_score": 2.31,
      "sell_score": 2.5,
      "final_score": 2.31,
      "signal": "BUY",
      "confidence": 0.332,
      "regime": "recovery",
      "signals_fired": [
        "rsi_oversold",
        "momentum_down"
      ],
      "timestamp": "2026-03-13T21:49:51.450077",
      "symbol": "ETH/USD"
    },
    "SOL/USD": {
      "price": 88.709,
      "rsi": 6.93,
      "sma3": 88.836833,
      "sma9": 89.5528,
      "sma21": 89.572476,
      "sma50": 87.759476,
      "macd_hist": -0.279958,
      "bb_pct": 0.272,
      "vol_ratio": 0.065,
      "vol_strong": false,
      "rsi_divergence": "none",
      "trend_slope": -0.1676,
      "trend_1h": 0.0,
      "trend_4h": -0.0016,
      "trend_24h": 0.1153,
      "stabilising": true,
      "near_support": false,
      "atr_pct": 0.0139,
      "dynamic_stop": 0.03,
      "dynamic_tp": 0.0277,
      "buy_score": 3.0,
      "sell_score": 4.5,
      "final_score": 3.0,
      "signal": "BUY",
      "confidence": 0.35,
      "regime": "recovery",
      "signals_fired": [
        "trend_bear",
        "rsi_oversold",
        "momentum_down",
        "stabilising"
      ],
      "timestamp": "2026-03-13T21:49:51.454972",
      "symbol": "SOL/USD"
    },
    "DOGE/USD": {
      "price": 0.0962925,
      "rsi": 24.22,
      "sma3": 0.096287,
      "sma9": 0.097188,
      "sma21": 0.09744,
      "sma50": 0.095247,
      "macd_hist": -0.000421,
      "bb_pct": 0.312,
      "vol_ratio": 0.0,
      "vol_strong": false,
      "rsi_divergence": "none",
      "trend_slope": -0.2393,
      "trend_1h": 0.0,
      "trend_4h": 0.0044,
      "trend_24h": 0.0804,
      "stabilising": false,
      "near_support": false,
      "atr_pct": 0.0152,
      "dynamic_stop": 0.03,
      "dynamic_tp": 0.0305,
      "buy_score": 2.31,
      "sell_score": 4.5,
      "final_score": 2.31,
      "signal": "BUY",
      "confidence": 0.332,
      "regime": "recovery",
      "signals_fired": [
        "trend_bear",
        "rsi_oversold",
        "momentum_down"
      ],
      "timestamp": "2026-03-13T21:49:51.459805",
      "symbol": "DOGE/USD"
    },
    "AVAX/USD": {
      "price": 9.77215,
      "rsi": 15.89,
      "sma3": 9.780337,
      "sma9": 9.873418,
      "sma21": 9.912609,
      "sma50": 9.723763,
      "macd_hist": -0.0373,
      "bb_pct": 0.204,
      "vol_ratio": 0.002,
      "vol_strong": false,
      "rsi_divergence": "none",
      "trend_slope": -0.2157,
      "trend_1h": 0.0,
      "trend_4h": -0.0006,
      "trend_24h": 0.0541,
      "stabilising": true,
      "near_support": false,
      "atr_pct": 0.0145,
      "dynamic_stop": 0.03,
      "dynamic_tp": 0.0289,
      "buy_score": 3.0,
      "sell_score": 4.5,
      "final_score": 3.0,
      "signal": "BUY",
      "confidence": 0.35,
      "regime": "recovery",
      "signals_fired": [
        "trend_bear",
        "rsi_oversold",
        "momentum_down",
        "stabilising"
      ],
      "timestamp": "2026-03-13T21:49:51.464622",
      "symbol": "AVAX/USD"
    },
    "LINK/USD": {
      "price": 9.15403,
      "rsi": 21.08,
      "sma3": 9.157362,
      "sma9": 9.242781,
      "sma21": 9.255227,
      "sma50": 9.108608,
      "macd_hist": -0.028809,
      "bb_pct": 0.246,
      "vol_ratio": 0.0,
      "vol_strong": false,
      "rsi_divergence": "none",
      "trend_slope": -0.2335,
      "trend_1h": 0.0,
      "trend_4h": 0.0029,
      "trend_24h": 0.0673,
      "stabilising": false,
      "near_support": false,
      "atr_pct": 0.0142,
      "dynamic_stop": 0.03,
      "dynamic_tp": 0.0284,
      "buy_score": 2.31,
      "sell_score": 4.5,
      "final_score": 2.31,
      "signal": "BUY",
      "confidence": 0.332,
      "regime": "recovery",
      "signals_fired": [
        "trend_bear",
        "rsi_oversold",
        "momentum_down"
      ],
      "timestamp": "2026-03-13T21:49:51.469398",
      "symbol": "LINK/USD"
    },
    "XRP/USD": {
      "price": 1.40121,
      "rsi": 33.87,
      "sma3": 1.401792,
      "sma9": 1.409337,
      "sma21": 1.415229,
      "sma50": 1.395544,
      "macd_hist": -0.003981,
      "bb_pct": 0.247,
      "vol_ratio": 0.188,
      "vol_strong": false,
      "rsi_divergence": "none",
      "trend_slope": -0.098,
      "trend_1h": 0.0,
      "trend_4h": 0.0026,
      "trend_24h": 0.0645,
      "stabilising": true,
      "near_support": true,
      "atr_pct": 0.012,
      "dynamic_stop": 0.03,
      "dynamic_tp": 0.0239,
      "buy_score": 4.5,
      "sell_score": 2.5,
      "final_score": 4.5,
      "signal": "BUY",
      "confidence": 0.39,
      "regime": "recovery",
      "signals_fired": [
        "trend_bear",
        "rsi_oversold",
        "near_support",
        "stabilising"
      ],
      "timestamp": "2026-03-13T21:49:51.474227",
      "symbol": "XRP/USD"
    },
    "LTC/USD": {
      "price": 55.76,
      "rsi": 54.31,
      "sma3": 55.71345,
      "sma9": 55.676639,
      "sma21": 55.532581,
      "sma50": 54.925704,
      "macd_hist": -0.036254,
      "bb_pct": 0.631,
      "vol_ratio": 0.0,
      "vol_strong": false,
      "rsi_divergence": "none",
      "trend_slope": 0.0208,
      "trend_1h": 0.0,
      "trend_4h": 0.0068,
      "trend_24h": 0.0955,
      "stabilising": false,
      "near_support": false,
      "atr_pct": 0.0101,
      "dynamic_stop": 0.03,
      "dynamic_tp": 0.0202,
      "buy_score": 4.62,
      "sell_score": 0.5,
      "final_score": 4.62,
      "signal": "BUY",
      "confidence": 0.393,
      "regime": "recovery",
      "signals_fired": [
        "trend_bull",
        "ma_cross_bull"
      ],
      "timestamp": "2026-03-13T21:49:51.479175",
      "symbol": "LTC/USD"
    },
    "BCH/USD": {
      "price": 463.5775,
      "rsi": 41.41,
      "sma3": 463.570667,
      "sma9": 464.625222,
      "sma21": 466.430286,
      "sma50": 460.57385,
      "macd_hist": -0.908629,
      "bb_pct": 0.229,
      "vol_ratio": 0.751,
      "vol_strong": false,
      "rsi_divergence": "none",
      "trend_slope": -0.0373,
      "trend_1h": 0.0,
      "trend_4h": -0.0019,
      "trend_24h": 0.0785,
      "stabilising": false,
      "near_support": true,
      "atr_pct": 0.0091,
      "dynamic_stop": 0.03,
      "dynamic_tp": 0.0182,
      "buy_score": 4.95,
      "sell_score": 2.5,
      "final_score": 4.95,
      "signal": "BUY",
      "confidence": 0.402,
      "regime": "recovery",
      "signals_fired": [
        "trend_bear",
        "rsi_oversold",
        "near_support"
      ],
      "timestamp": "2026-03-13T21:49:51.483910",
      "symbol": "BCH/USD"
    },
    "DOT/USD": {
      "price": 1.4638,
      "rsi": 3.19,
      "sma3": 1.468202,
      "sma9": 1.492587,
      "sma21": 1.509016,
      "sma50": 1.51123,
      "macd_hist": -0.006468,
      "bb_pct": 0.022,
      "vol_ratio": 0.0,
      "vol_strong": false,
      "rsi_divergence": "none",
      "trend_slope": -0.516,
      "trend_1h": 0.0,
      "trend_4h": -0.0076,
      "trend_24h": -0.1461,
      "stabilising": true,
      "near_support": true,
      "atr_pct": 0.0123,
      "dynamic_stop": 0.03,
      "dynamic_tp": 0.0245,
      "buy_score": 3.85,
      "sell_score": 5.0,
      "final_score": 3.85,
      "signal": "BUY",
      "confidence": 0.373,
      "regime": "recovery",
      "signals_fired": [
        "trend_bear",
        "rsi_oversold",
        "bb_lower",
        "near_support",
        "momentum_down",
        "stabilising"
      ],
      "timestamp": "2026-03-13T21:49:51.488605",
      "symbol": "DOT/USD"
    },
    "UNI/USD": {
      "price": 4.035,
      "rsi": 11.96,
      "sma3": 4.033843,
      "sma9": 4.067961,
      "sma21": 4.047534,
      "sma50": 3.961295,
      "macd_hist": -0.010713,
      "bb_pct": 0.428,
      "vol_ratio": 0.265,
      "vol_strong": false,
      "rsi_divergence": "none",
      "trend_slope": -0.2649,
      "trend_1h": 0.0,
      "trend_4h": 0.0018,
      "trend_24h": 0.1355,
      "stabilising": false,
      "near_support": false,
      "atr_pct": 0.0146,
      "dynamic_stop": 0.03,
      "dynamic_tp": 0.0292,
      "buy_score": 2.31,
      "sell_score": 2.5,
      "final_score": 2.31,
      "signal": "BUY",
      "confidence": 0.332,
      "regime": "recovery",
      "signals_fired": [
        "rsi_oversold",
        "momentum_down"
      ],
      "timestamp": "2026-03-13T21:49:51.493425",
      "symbol": "UNI/USD"
    },
    "AAVE/USD": {
      "price": 113.13,
      "rsi": 28.13,
      "sma3": 113.17,
      "sma9": 114.086611,
      "sma21": 114.717881,
      "sma50": 112.03383,
      "macd_hist": -0.457804,
      "bb_pct": 0.227,
      "vol_ratio": 0.0,
      "vol_strong": false,
      "rsi_divergence": "none",
      "trend_slope": -0.182,
      "trend_1h": 0.0,
      "trend_4h": 0.0038,
      "trend_24h": 0.0661,
      "stabilising": false,
      "near_support": false,
      "atr_pct": 0.0141,
      "dynamic_stop": 0.03,
      "dynamic_tp": 0.0282,
      "buy_score": 2.31,
      "sell_score": 4.5,
      "final_score": 2.31,
      "signal": "BUY",
      "confidence": 0.332,
      "regime": "recovery",
      "signals_fired": [
        "trend_bear",
        "rsi_oversold",
        "momentum_down"
      ],
      "timestamp": "2026-03-13T21:49:51.498170",
      "symbol": "AAVE/USD"
    },
    "SHIB/USD": {
      "price": 5.96e-06,
      "rsi": 21.88,
      "sma3": 6e-06,
      "sma9": 6e-06,
      "sma21": 6e-06,
      "sma50": 6e-06,
      "macd_hist": -0.0,
      "bb_pct": 0.323,
      "vol_ratio": 0.0,
      "vol_strong": false,
      "rsi_divergence": "none",
      "trend_slope": -0.2479,
      "trend_1h": 0.0,
      "trend_4h": 0.0025,
      "trend_24h": 0.0495,
      "stabilising": false,
      "near_support": false,
      "atr_pct": 0.0427,
      "dynamic_stop": 0.06,
      "dynamic_tp": 0.08,
      "buy_score": 2.31,
      "sell_score": 4.5,
      "final_score": 2.31,
      "signal": "BUY",
      "confidence": 0.332,
      "regime": "recovery",
      "signals_fired": [
        "trend_bear",
        "rsi_oversold",
        "momentum_down"
      ],
      "timestamp": "2026-03-13T21:49:51.502870",
      "symbol": "SHIB/USD"
    },
    "PEPE/USD": {
      "price": 3.4e-06,
      "rsi": 13.64,
      "sma3": 3e-06,
      "sma9": 3e-06,
      "sma21": 3e-06,
      "sma50": 3e-06,
      "macd_hist": -0.0,
      "bb_pct": 0.235,
      "vol_ratio": 0.0,
      "vol_strong": false,
      "rsi_divergence": "none",
      "trend_slope": -0.3831,
      "trend_1h": 0.0,
      "trend_4h": 0.0,
      "trend_24h": 0.0559,
      "stabilising": false,
      "near_support": false,
      "atr_pct": 0.1811,
      "dynamic_stop": 0.06,
      "dynamic_tp": 0.08,
      "buy_score": 2.31,
      "sell_score": 4.5,
      "final_score": 2.31,
      "signal": "BUY",
      "confidence": 0.332,
      "regime": "recovery",
      "signals_fired": [
        "trend_bear",
        "rsi_oversold",
        "momentum_down"
      ],
      "timestamp": "2026-03-13T21:49:51.507494",
      "symbol": "PEPE/USD"
    }
  },
  "last_run": "2026-03-13T21:49:51.508298",
  "daily_trades": 3,
  "trade_date": "2026-03-13",
  "peak_prices": {
    "DOTUSD": 1.5353,
    "BTCUSD": 71482.42
  },
  "total_trades": 5,
  "wins": 2,
  "losses": 1,
  "account": {
    "portfolio_value": 68.67,
    "cash": 6.96,
    "buying_power": 6.96,
    "equity": 68.67,
    "status": "ACTIVE"
  }
}