{
  "trades": [
    {
      "id": "5efb146e-e82f-4c5e-ab41-449ff2b3e93c",
      "symbol": "SHIBUSD",
      "qty": 1067120.95,
      "side": "buy",
      "reason": "signal_buy score=5.0 conf=0.5",
      "time": "2026-03-12T20:39:21.124318",
      "price": 5.87e-06
    }
  ],
  "signals": {
    "BTC/USD": {
      "price": 70333.145,
      "rsi": 48.525655120740694,
      "sma_short": 70141.96091666666,
      "sma_long": 69955.47605555555,
      "macd": 40.85145140916575,
      "macd_signal": 13.132841883287906,
      "macd_hist": 27.71860952587784,
      "bb_low": 69170.23246147404,
      "bb_up": 70662.96698852598,
      "vol_ratio": 0.0,
      "buy_score": 2.0,
      "sell_score": 0.0,
      "signal": "BULLISH",
      "timestamp": "2026-03-12T21:05:11.117389",
      "confidence": 0.32,
      "symbol": "BTC/USD"
    },
    "ETH/USD": {
      "price": 2065.9,
      "rsi": 50.31620476918018,
      "sma_short": 2064.621166666667,
      "sma_long": 2052.4518055555554,
      "macd": 5.329833100298401,
      "macd_signal": 4.368388958036171,
      "macd_hist": 0.9614441422622306,
      "bb_low": 2015.6151331350839,
      "bb_up": 2085.9015168649166,
      "vol_ratio": 0.39009602676992317,
      "buy_score": 2.0,
      "sell_score": 0.0,
      "signal": "BULLISH",
      "timestamp": "2026-03-12T21:05:11.119934",
      "confidence": 0.32,
      "symbol": "ETH/USD"
    },
    "SOL/USD": {
      "price": 86.54255,
      "rsi": 42.79784734020377,
      "sma_short": 86.42911666666667,
      "sma_long": 86.12201944444445,
      "macd": 0.09331811260157963,
      "macd_signal": 0.05993525612032316,
      "macd_hist": 0.03338285648125647,
      "bb_low": 84.690372646093,
      "bb_up": 87.45573235390701,
      "vol_ratio": 0.021179312454140644,
      "buy_score": 2.0,
      "sell_score": 0.0,
      "signal": "BULLISH",
      "timestamp": "2026-03-12T21:05:11.122306",
      "confidence": 0.32,
      "symbol": "SOL/USD"
    },
    "DOGE/USD": {
      "price": 0.094355,
      "rsi": 38.49791121516766,
      "sma_short": 0.09416005,
      "sma_long": 0.09361623333333333,
      "macd": 0.00033256466614865754,
      "macd_signal": 0.0002639149285361896,
      "macd_hist": 6.864973761246796e-05,
      "bb_low": 0.09128337067633276,
      "bb_up": 0.09565008432366724,
      "vol_ratio": 0.0,
      "buy_score": 2.0,
      "sell_score": 0.0,
      "signal": "BULLISH",
      "timestamp": "2026-03-12T21:05:11.124674",
      "confidence": 0.32,
      "symbol": "DOGE/USD"
    },
    "AVAX/USD": {
      "price": 9.63065,
      "rsi": 52.73545809606151,
      "sma_short": 9.59134,
      "sma_long": 9.564635833333334,
      "macd": 0.00752196628807944,
      "macd_signal": 0.0006227187084054534,
      "macd_hist": 0.006899247579673987,
      "bb_low": 9.449103814889202,
      "bb_up": 9.663922185110795,
      "vol_ratio": 0.0,
      "buy_score": 2.0,
      "sell_score": 0.0,
      "signal": "BULLISH",
      "timestamp": "2026-03-12T21:05:11.126882",
      "confidence": 0.32,
      "symbol": "AVAX/USD"
    },
    "LINK/USD": {
      "price": 8.987,
      "rsi": 43.17253853622206,
      "sma_short": 9.004175833333333,
      "sma_long": 8.977733333333333,
      "macd": 0.003958238635158651,
      "macd_signal": 0.0037499532217152307,
      "macd_hist": 0.00020828541344342002,
      "bb_low": 8.847077297389147,
      "bb_up": 9.09530670261085,
      "vol_ratio": 0.0,
      "buy_score": 2.0,
      "sell_score": 0.0,
      "signal": "BULLISH",
      "timestamp": "2026-03-12T21:05:11.129089",
      "confidence": 0.32,
      "symbol": "LINK/USD"
    },
    "XRP/USD": {
      "price": 1.374855,
      "rsi": 36.99065600616498,
      "sma_short": 1.37597,
      "sma_long": 1.3778847222222224,
      "macd": -0.0023424730880006184,
      "macd_signal": -0.001866373832628009,
      "macd_hist": -0.00047609925537260935,
      "bb_low": 1.3652708554960753,
      "bb_up": 1.3899466445039244,
      "vol_ratio": 0.0,
      "buy_score": 0.0,
      "sell_score": 1.0,
      "signal": "BEARISH",
      "timestamp": "2026-03-12T21:05:11.131299",
      "confidence": 0.2,
      "symbol": "XRP/USD"
    },
    "LTC/USD": {
      "price": 54.21725,
      "rsi": 37.64053479185638,
      "sma_short": 54.223833333333324,
      "sma_long": 54.27201111111111,
      "macd": -0.055956962169744884,
      "macd_signal": -0.030422430914111974,
      "macd_hist": -0.02553453125563291,
      "bb_low": 53.95019546361103,
      "bb_up": 54.629974536388964,
      "vol_ratio": 0.0,
      "buy_score": 0.0,
      "sell_score": 1.0,
      "signal": "BEARISH",
      "timestamp": "2026-03-12T21:05:11.133563",
      "confidence": 0.2,
      "symbol": "LTC/USD"
    },
    "BCH/USD": {
      "price": 454.574,
      "rsi": 36.18378840807028,
      "sma_short": 455.54425,
      "sma_long": 455.8350555555556,
      "macd": 0.3859942942043517,
      "macd_signal": 0.830445187005862,
      "macd_hist": -0.4444508928015103,
      "bb_low": 451.6857673889815,
      "bb_up": 459.7404326110184,
      "vol_ratio": 0.0,
      "buy_score": 0.0,
      "sell_score": 1.0,
      "signal": "BEARISH",
      "timestamp": "2026-03-12T21:05:11.135713",
      "confidence": 0.2,
      "symbol": "BCH/USD"
    },
    "DOT/USD": {
      "price": 1.510275,
      "rsi": 55.908314350797475,
      "sma_short": 1.5050466666666666,
      "sma_long": 1.5053391666666667,
      "macd": -0.0018671521467399366,
      "macd_signal": -0.002173546630005856,
      "macd_hist": 0.00030639448326591923,
      "bb_low": 1.4921401880977814,
      "bb_up": 1.5190383119022188,
      "vol_ratio": 0.0,
      "buy_score": 3.0,
      "sell_score": 0.0,
      "signal": "BULLISH",
      "timestamp": "2026-03-12T21:05:11.137874",
      "confidence": 0.38,
      "symbol": "DOT/USD"
    },
    "UNI/USD": {
      "price": 3.8934,
      "rsi": 38.74320241691858,
      "sma_short": 3.8962758333333336,
      "sma_long": 3.891754166666667,
      "macd": 0.002345223353016568,
      "macd_signal": 0.0030539626086806626,
      "macd_hist": -0.0007087392556640948,
      "bb_low": 3.8430862774569685,
      "bb_up": 3.9354957225430316,
      "vol_ratio": 0.0,
      "buy_score": 0.0,
      "sell_score": 1.0,
      "signal": "BEARISH",
      "timestamp": "2026-03-12T21:05:11.140023",
      "confidence": 0.2,
      "symbol": "UNI/USD"
    },
    "AAVE/USD": {
      "price": 110.85,
      "rsi": 52.69067426842744,
      "sma_short": 110.32208333333334,
      "sma_long": 109.48936111111111,
      "macd": 0.07710881756716503,
      "macd_signal": -0.15403407106738062,
      "macd_hist": 0.23114288863454566,
      "bb_low": 107.09668600071168,
      "bb_up": 111.70911399928832,
      "vol_ratio": 0.0,
      "buy_score": 2.0,
      "sell_score": 0.0,
      "signal": "BULLISH",
      "timestamp": "2026-03-12T21:05:11.142264",
      "confidence": 0.32,
      "symbol": "AAVE/USD"
    },
    "SHIB/USD": {
      "price": 5.87e-06,
      "rsi": 28.3333333333333,
      "sma_short": 5.8783333333333335e-06,
      "sma_long": 5.860277777777778e-06,
      "macd": 3.657961525680944e-08,
      "macd_signal": 4.2799959586708226e-08,
      "macd_hist": -6.220344329898788e-09,
      "bb_low": 5.659839933763142e-06,
      "bb_up": 6.036160066236859e-06,
      "vol_ratio": 0.0,
      "buy_score": 5.0,
      "sell_score": 1.0,
      "signal": "BUY",
      "timestamp": "2026-03-12T21:05:11.144434",
      "confidence": 0.5,
      "symbol": "SHIB/USD"
    },
    "PEPE/USD": {
      "price": 3.325e-06,
      "rsi": 48.64864864864866,
      "sma_short": 3.3175e-06,
      "sma_long": 3.3024999999999997e-06,
      "macd": 1.3079337690141944e-09,
      "macd_signal": -2.444215532082564e-09,
      "macd_hist": 3.752149301096758e-09,
      "bb_low": 3.254957517008667e-06,
      "bb_up": 3.3495424829913322e-06,
      "vol_ratio": 0.0,
      "buy_score": 2.0,
      "sell_score": 0.0,
      "signal": "BULLISH",
      "timestamp": "2026-03-12T21:05:11.146560",
      "confidence": 0.32,
      "symbol": "PEPE/USD"
    }
  },
  "last_run": "2026-03-12T21:05:11.146732",
  "daily_trades": 1,
  "trade_date": "2026-03-12",
  "peak_prices": {
    "SHIBUSD": 5.89e-06
  },
  "total_trades": 1,
  "wins": 0,
  "losses": 0,
  "account": {
    "portfolio_value": 68.67,
    "cash": 6.96,
    "buying_power": 6.96,
    "equity": 68.67,
    "status": "ACTIVE"
  }
}