{
  "trades": [
    {
      "id": "5efb146e-e82f-4c5e-ab41-449ff2b3e93c",
      "symbol": "SHIBUSD",
      "qty": 1067120.95,
      "side": "buy",
      "reason": "signal_buy score=5.0 conf=0.5",
      "time": "2026-03-12T20:39:21.124318",
      "price": 5.87e-06
    },
    {
      "id": "ab0b469e-140d-41e4-b6cd-24035278a2f7",
      "symbol": "SHIBUSD",
      "qty": 1064453.147625,
      "side": "sell",
      "reason": "signal_sell score=1.0",
      "time": "2026-03-12T23:01:55.336558"
    },
    {
      "id": "d61987b1-208d-46ec-9f71-f8bf278918d4",
      "symbol": "LTCUSD",
      "qty": 0.1143135,
      "side": "sell",
      "reason": "signal_sell score=6.0",
      "time": "2026-03-13T00:15:59.175162"
    },
    {
      "id": "c162bc03-a8d0-4600-abee-127456d29e97",
      "symbol": "DOTUSD",
      "qty": 4.119675,
      "side": "sell",
      "reason": "signal_sell score=2.0",
      "time": "2026-03-13T10:01:26.594817"
    },
    {
      "id": "7af9bdee-1cf2-4732-a297-bca6ac46b32d",
      "symbol": "DOTUSD",
      "qty": 4.05,
      "side": "buy",
      "reason": "signal_buy score=4.0 conf=0.44",
      "time": "2026-03-13T13:03:09.377437",
      "price": 1.534195
    }
  ],
  "signals": {
    "BTC/USD": {
      "price": 71406.705,
      "rsi": 29.694185864468224,
      "sma_short": 71318.32183333334,
      "sma_long": 71737.65211111112,
      "macd": 164.16997152545082,
      "macd_signal": 335.0089105098563,
      "macd_hist": -170.8389389844055,
      "bb_low": 70515.44767651982,
      "bb_up": 73040.06942348018,
      "vol_ratio": 0.028580409294360554,
      "buy_score": 4.0,
      "sell_score": 2.0,
      "signal": "BUY",
      "timestamp": "2026-03-13T21:18:37.529259",
      "confidence": 0.44,
      "symbol": "BTC/USD"
    },
    "ETH/USD": {
      "price": 2112.95,
      "rsi": 26.270708892144256,
      "sma_short": 2108.8428333333336,
      "sma_long": 2125.670666666667,
      "macd": 8.524953817598998,
      "macd_signal": 13.62932916050352,
      "macd_hist": -5.104375342904522,
      "bb_low": 2074.9231670080726,
      "bb_up": 2163.6540829919277,
      "vol_ratio": 0.04769423880074883,
      "buy_score": 4.0,
      "sell_score": 2.0,
      "signal": "BUY",
      "timestamp": "2026-03-13T21:18:37.531999",
      "confidence": 0.44,
      "symbol": "ETH/USD"
    },
    "SOL/USD": {
      "price": 88.9225,
      "rsi": 12.817739318550366,
      "sma_short": 88.908,
      "sma_long": 89.57652222222222,
      "macd": 0.3699422480857635,
      "macd_signal": 0.6362749772617946,
      "macd_hist": -0.2663327291760311,
      "bb_low": 87.7616823554769,
      "bb_up": 91.3156726445231,
      "vol_ratio": 0.0,
      "buy_score": 4.0,
      "sell_score": 2.0,
      "signal": "BUY",
      "timestamp": "2026-03-13T21:18:37.534607",
      "confidence": 0.44,
      "symbol": "SOL/USD"
    },
    "DOGE/USD": {
      "price": 0.096635,
      "rsi": 29.5918367346939,
      "sma_short": 0.09640151666666667,
      "sma_long": 0.09722603888888888,
      "macd": 0.0003485974969097694,
      "macd_signal": 0.0007475626161373037,
      "macd_hist": -0.00039896511922753435,
      "bb_low": 0.09440508641010228,
      "bb_up": 0.10054452858989774,
      "vol_ratio": 0.0,
      "buy_score": 4.0,
      "sell_score": 2.0,
      "signal": "BUY",
      "timestamp": "2026-03-13T21:18:37.537279",
      "confidence": 0.44,
      "symbol": "DOGE/USD"
    },
    "AVAX/USD": {
      "price": 9.80887,
      "rsi": 25.27597402597391,
      "sma_short": 9.792576666666667,
      "sma_long": 9.877497777777778,
      "macd": 0.020703945199764817,
      "macd_signal": 0.055660657989660446,
      "macd_hist": -0.03495671278989563,
      "bb_low": 9.682699312297144,
      "bb_up": 10.141701687702858,
      "vol_ratio": 0.0,
      "buy_score": 4.0,
      "sell_score": 2.0,
      "signal": "BUY",
      "timestamp": "2026-03-13T21:18:37.539848",
      "confidence": 0.44,
      "symbol": "AVAX/USD"
    },
    "LINK/USD": {
      "price": 9.177,
      "rsi": 24.05127708040493,
      "sma_short": 9.165018333333334,
      "sma_long": 9.245332777777778,
      "macd": 0.018553266978054594,
      "macd_signal": 0.04589612696340678,
      "macd_hist": -0.027342859985352186,
      "bb_low": 9.062406569706088,
      "bb_up": 9.443772930293914,
      "vol_ratio": 0.0,
      "buy_score": 4.0,
      "sell_score": 2.0,
      "signal": "BUY",
      "timestamp": "2026-03-13T21:18:37.542462",
      "confidence": 0.44,
      "symbol": "LINK/USD"
    },
    "XRP/USD": {
      "price": 1.4045,
      "rsi": 40.33629686896033,
      "sma_short": 1.4028883333333333,
      "sma_long": 1.4097027777777777,
      "macd": 0.0018352106109402744,
      "macd_signal": 0.0056065171659543285,
      "macd_hist": -0.003771306555014054,
      "bb_low": 1.3879654993254817,
      "bb_up": 1.4429945006745184,
      "vol_ratio": 0.03645082442798866,
      "buy_score": 4.0,
      "sell_score": 2.0,
      "signal": "BUY",
      "timestamp": "2026-03-13T21:18:37.544956",
      "confidence": 0.44,
      "symbol": "XRP/USD"
    },
    "LTC/USD": {
      "price": 55.9415,
      "rsi": 63.68593238822242,
      "sma_short": 55.77394999999999,
      "sma_long": 55.69680555555555,
      "macd": 0.2546740564644594,
      "macd_signal": 0.2793454895391144,
      "macd_hist": -0.024671433074655025,
      "bb_low": 54.72035104145151,
      "bb_up": 56.38721895854847,
      "vol_ratio": 0.0,
      "buy_score": 3.0,
      "sell_score": 5.0,
      "signal": "BUY",
      "timestamp": "2026-03-13T21:18:37.547483",
      "confidence": 0.38,
      "symbol": "LTC/USD"
    },
    "BCH/USD": {
      "price": 464.418,
      "rsi": 48.40983737883547,
      "sma_short": 463.85083333333324,
      "sma_long": 464.7186111111111,
      "macd": 0.9900769710758937,
      "macd_signal": 1.8450670250717136,
      "macd_hist": -0.85499005399582,
      "bb_low": 461.3269908427874,
      "bb_up": 471.53565915721265,
      "vol_ratio": 0.7505580792706724,
      "buy_score": 0.0,
      "sell_score": 1.0,
      "signal": "BEARISH",
      "timestamp": "2026-03-13T21:18:37.549981",
      "confidence": 0.2,
      "symbol": "BCH/USD"
    },
    "DOT/USD": {
      "price": 1.4705,
      "rsi": 3.687008784096193,
      "sma_short": 1.4704350000000002,
      "sma_long": 1.4933311111111112,
      "macd": -0.010634995718242113,
      "macd_signal": -0.004594235785709654,
      "macd_hist": -0.006040759932532459,
      "bb_low": 1.4633862541123541,
      "bb_up": 1.552179245887646,
      "vol_ratio": 0.0,
      "buy_score": 4.0,
      "sell_score": 2.0,
      "signal": "BUY",
      "timestamp": "2026-03-13T21:18:37.552468",
      "confidence": 0.44,
      "symbol": "DOT/USD"
    },
    "UNI/USD": {
      "price": 4.03811,
      "rsi": 12.422811478386905,
      "sma_short": 4.03488,
      "sma_long": 4.0683066666666665,
      "macd": 0.025936641781934888,
      "macd_signal": 0.036450728827901215,
      "macd_hist": -0.010514087045966326,
      "bb_low": 3.948009221440351,
      "bb_up": 4.151413778559648,
      "vol_ratio": 0.0,
      "buy_score": 4.0,
      "sell_score": 2.0,
      "signal": "BUY",
      "timestamp": "2026-03-13T21:18:37.554926",
      "confidence": 0.44,
      "symbol": "UNI/USD"
    },
    "AAVE/USD": {
      "price": 113.637,
      "rsi": 35.850495804729135,
      "sma_short": 113.339,
      "sma_long": 114.14294444444444,
      "macd": 0.3298529618324295,
      "macd_signal": 0.7553017200340043,
      "macd_hist": -0.4254487582015748,
      "bb_low": 111.9254752653799,
      "bb_up": 117.4741747346201,
      "vol_ratio": 0.0,
      "buy_score": 4.0,
      "sell_score": 2.0,
      "signal": "BUY",
      "timestamp": "2026-03-13T21:18:37.557432",
      "confidence": 0.44,
      "symbol": "AAVE/USD"
    },
    "SHIB/USD": {
      "price": 5.985e-06,
      "rsi": 27.586206896551985,
      "sma_short": 5.9749999999999995e-06,
      "sma_long": 6.0188888888888895e-06,
      "macd": 1.8802584519707004e-08,
      "macd_signal": 3.8994367995464056e-08,
      "macd_hist": -2.0191783475757052e-08,
      "bb_low": 5.848825204129034e-06,
      "bb_up": 6.198674795870966e-06,
      "vol_ratio": 0.0,
      "buy_score": 4.0,
      "sell_score": 2.0,
      "signal": "BUY",
      "timestamp": "2026-03-13T21:18:37.559912",
      "confidence": 0.44,
      "symbol": "SHIB/USD"
    },
    "PEPE/USD": {
      "price": 3.415e-06,
      "rsi": 21.739130434782453,
      "sma_short": 3.4033333333333335e-06,
      "sma_long": 3.4505555555555556e-06,
      "macd": 8.85977976279206e-09,
      "macd_signal": 2.8181324688547028e-08,
      "macd_hist": -1.9321544925754968e-08,
      "bb_low": 3.338972489755923e-06,
      "bb_up": 3.6055275102440764e-06,
      "vol_ratio": 0.0,
      "buy_score": 4.0,
      "sell_score": 2.0,
      "signal": "BUY",
      "timestamp": "2026-03-13T21:18:37.562362",
      "confidence": 0.44,
      "symbol": "PEPE/USD"
    }
  },
  "last_run": "2026-03-13T21:18:37.563402",
  "daily_trades": 3,
  "trade_date": "2026-03-13",
  "peak_prices": {
    "DOTUSD": 1.5353,
    "BTCUSD": 71468.8
  },
  "total_trades": 5,
  "wins": 2,
  "losses": 1,
  "account": {
    "portfolio_value": 68.67,
    "cash": 6.96,
    "buying_power": 6.96,
    "equity": 68.67,
    "status": "ACTIVE"
  }
}